Workbook
Name NativeTimeline_Travel_Date: #N/A
Name Slicer_Category: #N/A
Name Slicer_Channel: #N/A
Name Slicer_Destination: #N/A
Name Slicer_Traveler_Type: #N/A

Sheet DASHBOARD
A1: Dynamic Business Reporting Dashboard
A2: B2B Travel Performance Analytics | T2: Dashboard Filters

Sheet Pivot_Analysis
A3: Booking_Channels | B3: Revenue_Per_Channel | E3: Activities | F3: Bookings_Per_Activity | I3: Travel_Months | J3: Revenue_Per_Month
A4: B2B Email | B4: 330229 | E4: Island Hopping | F4: 74 | I4: 2024 | J4: 2351581
A5: B2B Website | B5: 355254 | E5: Yacht Cruise | F5: 65 | I5: Jan | J5: 28047
A6: Chathead | B6: 335127 | E6: Concert | F6: 64 | I6: Feb | J6: 86377
A7: Corporate Sales Team | B7: 326088 | E7: Museum Tour | F7: 63 | I7: Mar | J7: 182051
A8: Existing Client | B8: 357683 | E8: Beach Tour | F8: 63 | I8: Apr | J8: 234595
A9: Referral Partner | B9: 313723 | I9: May | J9: 166691
A10: Whatsapp | B10: 333477 | I10: Jun | J10: 192483
A11: Grand Total | B11: 2351581 | I11: Jul | J11: 249260
I12: Aug | J12: 207468
I13: Sep | J13: 244242
I14: Oct | J14: 285257
I15: Nov | J15: 192646
I16: Dec | J16: 282464
I17: Grand Total | J17: 2351581
A35: Traveler Type | B35: Bookings | C35: Revenue_Traveleler_Type
A36: Corporate | B36: 188 | C36: 472603
A37: Couple | B37: 161 | C37: 423138
A38: Family | B38: 194 | C38: 523144 | F38: Destinations | G38: Total_Revenue | H38: Profit_Per_Destination | I38: Total_Bookings
A39: Friends Group | B39: 178 | C39: 488817 | F39: Abu Dhabi | G39: 614484 | H39: 179456.06 | I39: 233
A40: Solo | B40: 169 | C40: 443879 | F40: Cape Town | G40: 606441 | H40: 178700.97 | I40: 225
F41: Bali | G41: 573337 | H41: 172756.85 | I41: 220
F42: Azerbaijan | G42: 557319 | H42: 173756.49 | I42: 212
F43: Grand Total | G43: 2351581 | H43: 704670.37 | I43: 890

Sheet KPI_Calculations
A1: KPI_Name | B1: Value
A2: Total Revenue | B2: =SUM(BookingRecords[Revenue]) -> 19606005
A3: Total Bookings | B3: =COUNTA(BookingRecords[Booking_ID]) -> 7500
A4: Avg Revenue Per Booking | B4: =AVERAGE(BookingRecords[Revenue]) -> 2614.134
A5: Avg Guests | B5: =AVERAGE(BookingRecords[Guests]) -> 4.4969333
A6: Highest Revenue Market | B6: =INDEX(Helper_Tables!A2:A16,MATCH(MAX(Helper_Tables!B2:B16),Helper_Tables!B2:B16,0),1) -> Hongkong
A7: Most Popular Activity | B7: =INDEX(Helper_Tables!D2:D17,MATCH(MAX(Helper_Tables!E2:E17),Helper_Tables!E2:E17,0)) -> Yacht Cruise
A8: Peak Month | B8: =INDEX(Helper_Tables!G2:G13,MATCH(MAX(Helper_Tables!H2:H13),Helper_Tables!H2:H13,0)) -> April
A9: Top Traveler Type | B9: =INDEX(Helper_Tables!J2:J6,MATCH(MAX(Helper_Tables!K2:K6),Helper_Tables!K2:K6,0)) -> Corporate

Sheet Helper_Tables
A1: Destination | B1: Revenue | D1: Activity | E1: Guests | G1: Month | H1: Revenue | J1: Traveler Type | K1: Guests
A2: {=_xlfn.UNIQUE(Raw_Data_Table!F7473:F7501)} -> Bali | B2: =SUMIFS(BookingRecords[Revenue],BookingRecords[Destination],Helper_Tables!A2) -> 1329611 | D2: {=_xlfn.UNIQUE(BookingRecords[Activity])} -> Jet Ski | E2: =COUNTIF(Raw_Data_Table!H2:H7501,Helper_Tables!D2) -> 364 | G2: {=_xlfn.UNIQUE(BookingRecords[Travel_Month])} -> November | H2: =SUMIFS(BookingRecords[Revenue],BookingRecords[Travel_Month],Helper_Tables!G2) -> 1501764 | J2: {=_xlfn.UNIQUE(BookingRecords[Traveler_Type])} -> Corporate | K2: =COUNTIF(BookingRecords[Traveler_Type],Helper_Tables!J2) -> 1520
A3: Indonesia | B3: =SUMIFS(BookingRecords[Revenue],BookingRecords[Destination],Helper_Tables!A3) -> 1196458 | D3: Sky Diving | E3: =COUNTIF(Raw_Data_Table!H3:H7502,Helper_Tables!D3) -> 394 | G3: August | H3: =SUMIFS(BookingRecords[Revenue],BookingRecords[Travel_Month],Helper_Tables!G3) -> 1712070 | J3: Couple | K3: =COUNTIF(BookingRecords[Traveler_Type],Helper_Tables!J3) -> 1503
A4: Dubai | B4: =SUMIFS(BookingRecords[Revenue],BookingRecords[Destination],Helper_Tables!A4) -> 1350387 | D4: Desert Safari | E4: =COUNTIF(Raw_Data_Table!H4:H7503,Helper_Tables!D4) -> 398 | G4: September | H4: =SUMIFS(BookingRecords[Revenue],BookingRecords[Travel_Month],Helper_Tables!G4) -> 1664005 | J4: Family | K4: =COUNTIF(BookingRecords[Traveler_Type],Helper_Tables!J4) -> 1501
A5: Egypt | B5: =SUMIFS(BookingRecords[Revenue],BookingRecords[Destination],Helper_Tables!A5) -> 1278471 | D5: Historical Walk | E5: =COUNTIF(Raw_Data_Table!H5:H7504,Helper_Tables!D5) -> 491 | G5: June | H5: =SUMIFS(BookingRecords[Revenue],BookingRecords[Travel_Month],Helper_Tables!G5) -> 1651690 | J5: Solo | K5: =COUNTIF(BookingRecords[Traveler_Type],Helper_Tables!J5) -> 1498
A6: Hongkong | B6: =SUMIFS(BookingRecords[Revenue],BookingRecords[Destination],Helper_Tables!A6) -> 1406695 | D6: Museum Tour | E6: =COUNTIF(Raw_Data_Table!H6:H7505,Helper_Tables!D6) -> 531 | G6: December | H6: =SUMIFS(BookingRecords[Revenue],BookingRecords[Travel_Month],Helper_Tables!G6) -> 1696990 | J6: Friends Group | K6: =COUNTIF(BookingRecords[Traveler_Type],Helper_Tables!J6) -> 1478
A7: Sharjah | B7: =SUMIFS(BookingRecords[Revenue],BookingRecords[Destination],Helper_Tables!A7) -> 1373625 | D7: Theme Park | E7: =COUNTIF(Raw_Data_Table!H7:H7506,Helper_Tables!D7) -> 465 | G7: March | H7: =SUMIFS(BookingRecords[Revenue],BookingRecords[Travel_Month],Helper_Tables!G7) -> 1607226
A8: Cape Town | B8: =SUMIFS(BookingRecords[Revenue],BookingRecords[Destination],Helper_Tables!A8) -> 1352241 | D8: Safari Park | E8: =COUNTIF(Raw_Data_Table!H8:H7507,Helper_Tables!D8) -> 508 | G8: January | H8: =SUMIFS(BookingRecords[Revenue],BookingRecords[Travel_Month],Helper_Tables!G8) -> 1639611
A9: Vietnam | B9: =SUMIFS(BookingRecords[Revenue],BookingRecords[Destination],Helper_Tables!A9) -> 1355710 | D9: Concert | E9: =COUNTIF(Raw_Data_Table!H9:H7508,Helper_Tables!D9) -> 482 | G9: July | H9: =SUMIFS(BookingRecords[Revenue],BookingRecords[Travel_Month],Helper_Tables!G9) -> 1621516
A10: Azerbaijan | B10: =SUMIFS(BookingRecords[Revenue],BookingRecords[Destination],Helper_Tables!A10) -> 1210717 | D10: VIP City Tour | E10: =COUNTIF(Raw_Data_Table!H10:H7509,Helper_Tables!D10) -> 507 | G10: April | H10: =SUMIFS(BookingRecords[Revenue],BookingRecords[Travel_Month],Helper_Tables!G10) -> 1785203
A11: Singapore | B11: =SUMIFS(BookingRecords[Revenue],BookingRecords[Destination],Helper_Tables!A11) -> 1120173 | D11: Temple Visit | E11: =COUNTIF(Raw_Data_Table!H11:H7510,Helper_Tables!D11) -> 476 | G11: October | H11: =SUMIFS(BookingRecords[Revenue],BookingRecords[Travel_Month],Helper_Tables!G11) -> 1688301
A12: Ras Al Khaimah | B12: =SUMIFS(BookingRecords[Revenue],BookingRecords[Destination],Helper_Tables!A12) -> 1363670 | D12: Yacht Cruise | E12: =COUNTIF(Raw_Data_Table!H12:H7511,Helper_Tables!D12) -> 537 | G12: May | H12: =SUMIFS(BookingRecords[Revenue],BookingRecords[Travel_Month],Helper_Tables!G12) -> 1546617
A13: Zanzibar | B13: =SUMIFS(BookingRecords[Revenue],BookingRecords[Destination],Helper_Tables!A13) -> 1190804 | D13: Nightlife Tour | E13: =COUNTIF(Raw_Data_Table!H13:H7512,Helper_Tables!D13) -> 526 | G13: February | H13: =SUMIFS(BookingRecords[Revenue],BookingRecords[Travel_Month],Helper_Tables!G13) -> 1491012
A14: Georgia | B14: =SUMIFS(BookingRecords[Revenue],BookingRecords[Destination],Helper_Tables!A14) -> 1332277 | D14: Beach Tour | E14: =COUNTIF(Raw_Data_Table!H14:H7513,Helper_Tables!D14) -> 499
A15: Thailand | B15: =SUMIFS(BookingRecords[Revenue],BookingRecords[Destination],Helper_Tables!A15) -> 1382812 | D15: Luxury Dinner | E15: =COUNTIF(Raw_Data_Table!H15:H7514,Helper_Tables!D15) -> 480
A16: Abu Dhabi | B16: =SUMIFS(BookingRecords[Revenue],BookingRecords[Destination],Helper_Tables!A16) -> 1362354 | D16: ATV Ride | E16: =COUNTIF(Raw_Data_Table!H16:H7515,Helper_Tables!D16) -> 347
D17: Island Hopping | E17: =COUNTIF(Raw_Data_Table!H17:H7516,Helper_Tables!D17) -> 495

Sheet Raw_Data_Table
A1: Booking_ID | B1: Booking_Date | C1: Travel_Date | D1: Travel_Month | E1: Country | F1: Destination | G1: Traveler_Type | H1: Activity | I1: Category | J1: Guests | K1: Revenue | L1: Cost | M1: Profit | N1: Discount | O1: Channel | P1: Booking_Status | Q1: Customer_Type | R1: Payment_Mode
A2: BK1001 | B2: 45946 | C2: 45963 | D2: November | E2: Israel | F2: Thailand | G2: Corporate | H2: Jet Ski | I2: Adventure | J2: 4 | K2: 2128 | L2: 1640.56 | M2: 487.44 | N2: 0.05 | O2: B2B Website | P2: Confirmed | Q2: New | R2: Bank Transfer
A3: BK1002 | B3: 45809 | C3: 45889 | D3: August | E3: Israel | F3: Cape Town | G3: Couple | H3: Sky Diving | I3: Adventure | J3: 7 | K3: 2105 | L3: 1529.87 | M3: 575.13 | N3: 0.15 | O3: Existing Client | P3: Confirmed | Q3: Repeat | R3: Bank Transfer
A4: BK1003 | B4: 45512 | C4: 45558 | D4: September | E4: Israel | F4: Cape Town | G4: Family | H4: Desert Safari | I4: Adventure | J4: 7 | K4: 1092 | L4: 878.24 | M4: 213.76 | N4: 0.1 | O4: Existing Client | P4: Confirmed | Q4: New | R4: Cash Collection
A5: BK1004 | B5: 45372 | C5: 45445 | D5: June | E5: Israel | F5: Cape Town | G5: Solo | H5: Historical Walk | I5: Culture | J5: 6 | K5: 1875 | L5: 1057.03 | M5: 817.97 | N5: 0 | O5: B2B Website | P5: Pending | Q5: New | R5: Cash Collection
A6: BK1005 | B6: 45576 | C6: 45637 | D6: December | E6: Israel | F6: Thailand | G6: Couple | H6: Museum Tour | I6: Culture | J6: 6 | K6: 3210 | L6: 2410.88 | M6: 799.12 | N6: 0.05 | O6: Referral Partner | P6: Confirmed | Q6: New | R6: Cash Collection
A7: BK1006 | B7: 45680 | C7: 45717 | D7: March | E7: Israel | F7: Bali | G7: Solo | H7: Theme Park | I7: Entertainment | J7: 6 | K7: 758 | L7: 603.78 | M7: 154.22 | N7: 0.05 | O7: B2B Website | P7: Confirmed | Q7: Repeat | R7: Bank Transfer
A8: BK1007 | B8: 45963 | C8: 46029 | D8: January | E8: Israel | F8: Hongkong | G8: Friends Group | H8: Safari Park | I8: Nature | J8: 8 | K8: 1470 | L8: 870.08 | M8: 599.92 | N8: 0.1 | O8: Chathead | P8: Pending | Q8: Repeat | R8: Cash Collection
A9: BK1008 | B9: 45516 | C9: 45536 | D9: September | E9: Israel | F9: Cape Town | G9: Corporate | H9: Concert | I9: Entertainment | J9: 2 | K9: 685 | L9: 408.16 | M9: 276.84 | N9: 0 | O9: Referral Partner | P9: Confirmed | Q9: Repeat | R9: Payment Link
A10: BK1009 | B10: 45771 | C10: 45841 | D10: July | E10: Israel | F10: Abu Dhabi | G10: Solo | H10: Historical Walk | I10: Culture | J10: 1 | K10: 1238 | L10: 959.78 | M10: 278.22 | N10: 0.2 | O10: Chathead | P10: Confirmed | Q10: New | R10: Payment Link
A11: BK1010 | B11: 45561 | C11: 45628 | D11: December | E11: Israel | F11: Vietnam | G11: Couple | H11: VIP City Tour | I11: Luxury | J11: 2 | K11: 2744 | L11: 2010.5 | M11: 733.5 | N11: 0.2 | O11: Referral Partner | P11: Cancelled | Q11: New | R11: Payment Link
A12: BK1011 | B12: 45623 | C12: 45688 | D12: January | E12: Israel | F12: Abu Dhabi | G12: Corporate | H12: Desert Safari | I12: Adventure | J12: 6 | K12: 2819 | L12: 1599.44 | M12: 1219.56 | N12: 0.05 | O12: Corporate Sales Team | P12: Confirmed | Q12: New | R12: Bank Transfer
A13: BK1012 | B13: 45967 | C13: 46030 | D13: January | E13: Israel | F13: Zanzibar | G13: Friends Group | H13: Theme Park | I13: Entertainment | J13: 5 | K13: 4622 | L13: 3128.82 | M13: 1493.18 | N13: 0.2 | O13: Corporate Sales Team | P13: Confirmed | Q13: New | R13: Payment Link
... A7501: BK8500 | B7501: 46005 | C7501: 46029 | D7501: January | E7501: Israel | F7501: Indonesia | G7501: Couple | H7501: Luxury Dinner | I7501: Luxury | J7501: 5 | K7501: 3100 | L7501: 1815.04 | M7501: 1284.96 | N7501: 0.2 | O7501: Chathead | P7501: Confirmed | Q7501: New | R7501: Bank Transfer
